[
  {
    "id": "288a501ef33780428925ff41ff992cbf",
    "type": "paragraph",
    "parentId": "286a501ef33780798745d087320edfc0",
    "curriculumId": "286a501ef33780798745d087320edfc0",
    "pageId": "286a501ef33780798745d087320edfc0",
    "data": {
      "color": "default",
      "parent": [
        {
          "annotations": {
            "bold": false,
            "code": false,
            "color": "default",
            "italic": false,
            "strikethrough": false,
            "underline": false
          },
          "plain_text": "練習問題2おつかれまさでした\n以下に練習問題2の回答例が記載されています。",
          "href": null
        }
      ]
    },
    "order": 0
  },
  {
    "id": "28aa501ef33780afb3b2ca9c7ee7ca74",
    "type": "heading_1",
    "parentId": "286a501ef33780798745d087320edfc0",
    "curriculumId": "286a501ef33780798745d087320edfc0",
    "pageId": "286a501ef33780798745d087320edfc0",
    "data": {
      "color": "default",
      "is_toggleable": false,
      "parent": [
        {
          "annotations": {
            "bold": false,
            "code": false,
            "color": "default",
            "italic": false,
            "strikethrough": false,
            "underline": false
          },
          "plain_text": "問題1",
          "href": null
        }
      ]
    },
    "order": 1
  },
  {
    "id": "28aa501ef33780c8992ff072f3613899",
    "type": "paragraph",
    "parentId": "286a501ef33780798745d087320edfc0",
    "curriculumId": "286a501ef33780798745d087320edfc0",
    "pageId": "286a501ef33780798745d087320edfc0",
    "data": {
      "color": "default",
      "parent": [
        {
          "annotations": {
            "bold": false,
            "code": false,
            "color": "default",
            "italic": false,
            "strikethrough": false,
            "underline": false
          },
          "plain_text": "2つの値をキーボードから入力して、その値同士を足し算し、計算結果を出力するプログラムを作成してください。",
          "href": null
        }
      ]
    },
    "order": 2
  },
  {
    "id": "28aa501ef337808c89dcf209ddf4adeb",
    "type": "paragraph",
    "parentId": "286a501ef33780798745d087320edfc0",
    "curriculumId": "286a501ef33780798745d087320edfc0",
    "pageId": "286a501ef33780798745d087320edfc0",
    "data": {
      "color": "default",
      "parent": [
        {
          "annotations": {
            "bold": false,
            "code": false,
            "color": "default",
            "italic": false,
            "strikethrough": false,
            "underline": false
          },
          "plain_text": "※プログラムは「prac2-1.py」として保存",
          "href": null
        }
      ]
    },
    "order": 3
  },
  {
    "id": "28aa501ef3378065b799d844a312e902",
    "type": "heading_3",
    "parentId": "286a501ef33780798745d087320edfc0",
    "curriculumId": "286a501ef33780798745d087320edfc0",
    "pageId": "286a501ef33780798745d087320edfc0",
    "data": {
      "color": "default",
      "is_toggleable": false,
      "parent": [
        {
          "annotations": {
            "bold": false,
            "code": false,
            "color": "default",
            "italic": false,
            "strikethrough": false,
            "underline": false
          },
          "plain_text": "期待する出力結果",
          "href": null
        }
      ]
    },
    "order": 4
  },
  {
    "id": "28aa501ef3378054bc6bdc62fcc43121",
    "type": "code",
    "parentId": "286a501ef33780798745d087320edfc0",
    "curriculumId": "286a501ef33780798745d087320edfc0",
    "pageId": "286a501ef33780798745d087320edfc0",
    "data": {
      "caption": [],
      "language": "plain text",
      "parent": [
        {
          "annotations": {
            "bold": false,
            "code": false,
            "color": "default",
            "italic": false,
            "strikethrough": false,
            "underline": false
          },
          "plain_text": "１つ目の値を入力してください:5\n２つ目の値を入力してください:9\n5 + 9 = 14 です。",
          "href": null
        }
      ]
    },
    "order": 5
  },
  {
    "id": "28aa501ef33780a8818dd8e20ab94e1e",
    "type": "paragraph",
    "parentId": "286a501ef33780798745d087320edfc0",
    "curriculumId": "286a501ef33780798745d087320edfc0",
    "pageId": "286a501ef33780798745d087320edfc0",
    "data": {
      "color": "default",
      "parent": [
        {
          "annotations": {
            "bold": false,
            "code": false,
            "color": "default",
            "italic": false,
            "strikethrough": false,
            "underline": false
          },
          "plain_text": "hint: 5+9 = 59は文字列同士の足し算です。",
          "href": null
        }
      ]
    },
    "order": 6
  },
  {
    "id": "288a501ef3378044a3efc833528c60a4",
    "type": "callout",
    "parentId": "286a501ef33780798745d087320edfc0",
    "curriculumId": "286a501ef33780798745d087320edfc0",
    "pageId": "286a501ef33780798745d087320edfc0",
    "data": {
      "color": "default_background",
      "icon": {
        "type": ""
      },
      "parent": [
        {
          "annotations": {
            "bold": false,
            "code": false,
            "color": "default",
            "italic": false,
            "strikethrough": false,
            "underline": false
          },
          "plain_text": "答え",
          "href": null
        }
      ]
    },
    "order": 7
  },
  {
    "id": "288a501ef337801b9240f7e47213d84a",
    "type": "code",
    "parentId": "288a501ef3378044a3efc833528c60a4",
    "curriculumId": "286a501ef33780798745d087320edfc0",
    "pageId": "286a501ef33780798745d087320edfc0",
    "data": {
      "caption": [],
      "language": "python",
      "parent": [
        {
          "annotations": {
            "bold": false,
            "code": false,
            "color": "default",
            "italic": false,
            "strikethrough": false,
            "underline": false
          },
          "plain_text": "# 2つの値をキーボードから入力して、その値同士を足し算し、計算結果を出力するプログラムを作成してください。\n\na = input(\"１つ目の値を入力してください:\")\nb = input(\"２つ目の値を入力してください:\")\na = int(a)\nb = int(b)\nprint(a,\"+\",b,\"=\",a+b,\"です。\")",
          "href": null
        }
      ]
    },
    "order": 0
  },
  {
    "id": "28aa501ef337804582d9d1a7aa35a978",
    "type": "heading_1",
    "parentId": "286a501ef33780798745d087320edfc0",
    "curriculumId": "286a501ef33780798745d087320edfc0",
    "pageId": "286a501ef33780798745d087320edfc0",
    "data": {
      "color": "default",
      "is_toggleable": false,
      "parent": [
        {
          "annotations": {
            "bold": false,
            "code": false,
            "color": "default",
            "italic": false,
            "strikethrough": false,
            "underline": false
          },
          "plain_text": "問題2",
          "href": null
        }
      ]
    },
    "order": 8
  },
  {
    "id": "28aa501ef337806c994be90fc61c6790",
    "type": "paragraph",
    "parentId": "286a501ef33780798745d087320edfc0",
    "curriculumId": "286a501ef33780798745d087320edfc0",
    "pageId": "286a501ef33780798745d087320edfc0",
    "data": {
      "color": "default",
      "parent": [
        {
          "annotations": {
            "bold": false,
            "code": false,
            "color": "default",
            "italic": false,
            "strikethrough": false,
            "underline": false
          },
          "plain_text": "問題1のプログラムを再利用して、結果の値が100以上なら「100以上ですね。」、100未満なら「100未満ですね。」と出力するプログラムを作成してください。",
          "href": null
        }
      ]
    },
    "order": 9
  },
  {
    "id": "28aa501ef33780679b5ad09dfc7903b0",
    "type": "paragraph",
    "parentId": "286a501ef33780798745d087320edfc0",
    "curriculumId": "286a501ef33780798745d087320edfc0",
    "pageId": "286a501ef33780798745d087320edfc0",
    "data": {
      "color": "default",
      "parent": [
        {
          "annotations": {
            "bold": false,
            "code": false,
            "color": "default",
            "italic": false,
            "strikethrough": false,
            "underline": false
          },
          "plain_text": "※プログラムは「prac2-2.py」として保存",
          "href": null
        }
      ]
    },
    "order": 10
  },
  {
    "id": "28aa501ef3378058b11ecc5b6119faa3",
    "type": "heading_3",
    "parentId": "286a501ef33780798745d087320edfc0",
    "curriculumId": "286a501ef33780798745d087320edfc0",
    "pageId": "286a501ef33780798745d087320edfc0",
    "data": {
      "color": "default",
      "is_toggleable": false,
      "parent": [
        {
          "annotations": {
            "bold": false,
            "code": false,
            "color": "default",
            "italic": false,
            "strikethrough": false,
            "underline": false
          },
          "plain_text": "期待する出力結果",
          "href": null
        }
      ]
    },
    "order": 11
  },
  {
    "id": "28aa501ef337802ba5eefa4753ef8580",
    "type": "code",
    "parentId": "286a501ef33780798745d087320edfc0",
    "curriculumId": "286a501ef33780798745d087320edfc0",
    "pageId": "286a501ef33780798745d087320edfc0",
    "data": {
      "caption": [],
      "language": "plain text",
      "parent": [
        {
          "annotations": {
            "bold": false,
            "code": false,
            "color": "default",
            "italic": false,
            "strikethrough": false,
            "underline": false
          },
          "plain_text": "１つ目の値を入力してください:50\n２つ目の値を入力してください:80\n50 + 80 = 130 です。\n100以上ですね。",
          "href": null
        }
      ]
    },
    "order": 12
  },
  {
    "id": "288a501ef33780a3854be90e42b6b1e0",
    "type": "callout",
    "parentId": "286a501ef33780798745d087320edfc0",
    "curriculumId": "286a501ef33780798745d087320edfc0",
    "pageId": "286a501ef33780798745d087320edfc0",
    "data": {
      "color": "default_background",
      "icon": {
        "type": ""
      },
      "parent": [
        {
          "annotations": {
            "bold": false,
            "code": false,
            "color": "default",
            "italic": false,
            "strikethrough": false,
            "underline": false
          },
          "plain_text": "答え",
          "href": null
        }
      ]
    },
    "order": 13
  },
  {
    "id": "288a501ef337804e81e3e483ff26604b",
    "type": "code",
    "parentId": "288a501ef33780a3854be90e42b6b1e0",
    "curriculumId": "286a501ef33780798745d087320edfc0",
    "pageId": "286a501ef33780798745d087320edfc0",
    "data": {
      "caption": [],
      "language": "python",
      "parent": [
        {
          "annotations": {
            "bold": false,
            "code": false,
            "color": "default",
            "italic": false,
            "strikethrough": false,
            "underline": false
          },
          "plain_text": "# 問題1のプログラムを再利用して、結果の値が100以上なら「100以上ですね。」、100以下なら「100以下ですね。」と出力するプログラムを作成してください。\n\na = input(\"１つ目の値を入力してください:\")\nb = input(\"２つ目の値を入力してください:\")\na = int(a)\nb = int(b)\nprint(a,\"+\",b,\"=\",a+b,\"です。\")\n\nif a+b \u003c 100:\n    print(\"100以下ですね。\")\nelse:\n    print(\"100以上ですね。\")",
          "href": null
        }
      ]
    },
    "order": 0
  },
  {
    "id": "28aa501ef33780848ce3ce574b780749",
    "type": "heading_1",
    "parentId": "286a501ef33780798745d087320edfc0",
    "curriculumId": "286a501ef33780798745d087320edfc0",
    "pageId": "286a501ef33780798745d087320edfc0",
    "data": {
      "color": "default",
      "is_toggleable": false,
      "parent": [
        {
          "annotations": {
            "bold": false,
            "code": false,
            "color": "default",
            "italic": false,
            "strikethrough": false,
            "underline": false
          },
          "plain_text": "問題3",
          "href": null
        }
      ]
    },
    "order": 14
  },
  {
    "id": "28aa501ef33780afa115df5cf787b04f",
    "type": "paragraph",
    "parentId": "286a501ef33780798745d087320edfc0",
    "curriculumId": "286a501ef33780798745d087320edfc0",
    "pageId": "286a501ef33780798745d087320edfc0",
    "data": {
      "color": "default",
      "parent": [
        {
          "annotations": {
            "bold": false,
            "code": false,
            "color": "default",
            "italic": false,
            "strikethrough": false,
            "underline": false
          },
          "plain_text": "ユーザーから入力された正答率を、次の表に従って評価し、その評価を出力するプログラムを作成してください。入力された正答率が不正な場合（100%を超過や0%未満）は「不正な正答率です」と出力するようにしてください。",
          "href": null
        }
      ]
    },
    "order": 15
  },
  {
    "id": "28aa501ef337808fb628e69ac538f391",
    "type": "table",
    "parentId": "286a501ef33780798745d087320edfc0",
    "curriculumId": "286a501ef33780798745d087320edfc0",
    "pageId": "286a501ef33780798745d087320edfc0",
    "data": {
      "has_column_header": true,
      "has_row_header": false,
      "table_width": 2
    },
    "order": 16
  },
  {
    "id": "28aa501ef33780b49559f37b121ea372",
    "type": "table_row",
    "parentId": "28aa501ef337808fb628e69ac538f391",
    "curriculumId": "286a501ef33780798745d087320edfc0",
    "pageId": "286a501ef33780798745d087320edfc0",
    "data": [
      [
        {
          "annotations": {
            "bold": false,
            "code": false,
            "color": "default",
            "italic": false,
            "strikethrough": false,
            "underline": false
          },
          "plain_text": "正答率",
          "href": null
        }
      ],
      [
        {
          "annotations": {
            "bold": false,
            "code": false,
            "color": "default",
            "italic": false,
            "strikethrough": false,
            "underline": false
          },
          "plain_text": "評価",
          "href": null
        }
      ]
    ],
    "order": 0
  },
  {
    "id": "28aa501ef33780518117d23f9c5d5cf8",
    "type": "table_row",
    "parentId": "28aa501ef337808fb628e69ac538f391",
    "curriculumId": "286a501ef33780798745d087320edfc0",
    "pageId": "286a501ef33780798745d087320edfc0",
    "data": [
      [
        {
          "annotations": {
            "bold": true,
            "code": false,
            "color": "default",
            "italic": false,
            "strikethrough": false,
            "underline": false
          },
          "plain_text": "90%以上 100%以下",
          "href": null
        }
      ],
      [
        {
          "annotations": {
            "bold": true,
            "code": false,
            "color": "default",
            "italic": false,
            "strikethrough": false,
            "underline": false
          },
          "plain_text": "秀",
          "href": null
        }
      ]
    ],
    "order": 1
  },
  {
    "id": "28aa501ef3378048be87c8b4eae9f925",
    "type": "table_row",
    "parentId": "28aa501ef337808fb628e69ac538f391",
    "curriculumId": "286a501ef33780798745d087320edfc0",
    "pageId": "286a501ef33780798745d087320edfc0",
    "data": [
      [
        {
          "annotations": {
            "bold": true,
            "code": false,
            "color": "default",
            "italic": false,
            "strikethrough": false,
            "underline": false
          },
          "plain_text": "80%以上 90%未満",
          "href": null
        },
        {
          "annotations": {
            "bold": false,
            "code": false,
            "color": "default",
            "italic": false,
            "strikethrough": false,
            "underline": false
          },
          "plain_text": " ",
          "href": null
        }
      ],
      [
        {
          "annotations": {
            "bold": true,
            "code": false,
            "color": "default",
            "italic": false,
            "strikethrough": false,
            "underline": false
          },
          "plain_text": "優",
          "href": null
        }
      ]
    ],
    "order": 2
  },
  {
    "id": "28aa501ef33780099394f9bf252b12a4",
    "type": "table_row",
    "parentId": "28aa501ef337808fb628e69ac538f391",
    "curriculumId": "286a501ef33780798745d087320edfc0",
    "pageId": "286a501ef33780798745d087320edfc0",
    "data": [
      [
        {
          "annotations": {
            "bold": true,
            "code": false,
            "color": "default",
            "italic": false,
            "strikethrough": false,
            "underline": false
          },
          "plain_text": "70%以上 80%未満",
          "href": null
        }
      ],
      [
        {
          "annotations": {
            "bold": true,
            "code": false,
            "color": "default",
            "italic": false,
            "strikethrough": false,
            "underline": false
          },
          "plain_text": "良",
          "href": null
        }
      ]
    ],
    "order": 3
  },
  {
    "id": "28aa501ef3378071a55fda2208bb103a",
    "type": "table_row",
    "parentId": "28aa501ef337808fb628e69ac538f391",
    "curriculumId": "286a501ef33780798745d087320edfc0",
    "pageId": "286a501ef33780798745d087320edfc0",
    "data": [
      [
        {
          "annotations": {
            "bold": true,
            "code": false,
            "color": "default",
            "italic": false,
            "strikethrough": false,
            "underline": false
          },
          "plain_text": "60%以上 70%未満",
          "href": null
        }
      ],
      [
        {
          "annotations": {
            "bold": true,
            "code": false,
            "color": "default",
            "italic": false,
            "strikethrough": false,
            "underline": false
          },
          "plain_text": "可",
          "href": null
        }
      ]
    ],
    "order": 4
  },
  {
    "id": "28aa501ef337805b9f86fe5fb9e8275d",
    "type": "table_row",
    "parentId": "28aa501ef337808fb628e69ac538f391",
    "curriculumId": "286a501ef33780798745d087320edfc0",
    "pageId": "286a501ef33780798745d087320edfc0",
    "data": [
      [
        {
          "annotations": {
            "bold": true,
            "code": false,
            "color": "default",
            "italic": false,
            "strikethrough": false,
            "underline": false
          },
          "plain_text": "0%以上 60%未満",
          "href": null
        }
      ],
      [
        {
          "annotations": {
            "bold": true,
            "code": false,
            "color": "default",
            "italic": false,
            "strikethrough": false,
            "underline": false
          },
          "plain_text": "不",
          "href": null
        }
      ]
    ],
    "order": 5
  },
  {
    "id": "28aa501ef337804990a3e5f8f2f9fb97",
    "type": "paragraph",
    "parentId": "286a501ef33780798745d087320edfc0",
    "curriculumId": "286a501ef33780798745d087320edfc0",
    "pageId": "286a501ef33780798745d087320edfc0",
    "data": {
      "color": "default",
      "parent": [
        {
          "annotations": {
            "bold": false,
            "code": false,
            "color": "default",
            "italic": false,
            "strikethrough": false,
            "underline": false
          },
          "plain_text": "ただし、ユーザーからは",
          "href": null
        },
        {
          "annotations": {
            "bold": true,
            "code": false,
            "color": "default",
            "italic": false,
            "strikethrough": false,
            "underline": false
          },
          "plain_text": "実数（少数を含む数字）が入力されることもある",
          "href": null
        },
        {
          "annotations": {
            "bold": false,
            "code": false,
            "color": "default",
            "italic": false,
            "strikethrough": false,
            "underline": false
          },
          "plain_text": "という想定でプログラムを作成してください。",
          "href": null
        }
      ]
    },
    "order": 17
  },
  {
    "id": "28aa501ef33780c5a295c8f967671d87",
    "type": "paragraph",
    "parentId": "286a501ef33780798745d087320edfc0",
    "curriculumId": "286a501ef33780798745d087320edfc0",
    "pageId": "286a501ef33780798745d087320edfc0",
    "data": {
      "color": "default",
      "parent": [
        {
          "annotations": {
            "bold": false,
            "code": false,
            "color": "default",
            "italic": false,
            "strikethrough": false,
            "underline": false
          },
          "plain_text": "また、必要な場合にはプログラム中の条件式にブール演算子を使用してください。",
          "href": null
        }
      ]
    },
    "order": 18
  },
  {
    "id": "28aa501ef33780b48d2acddef83d2ce8",
    "type": "paragraph",
    "parentId": "286a501ef33780798745d087320edfc0",
    "curriculumId": "286a501ef33780798745d087320edfc0",
    "pageId": "286a501ef33780798745d087320edfc0",
    "data": {
      "color": "default",
      "parent": [
        {
          "annotations": {
            "bold": false,
            "code": false,
            "color": "default",
            "italic": false,
            "strikethrough": false,
            "underline": false
          },
          "plain_text": "※プログラムは「prac2-3.py」として保存",
          "href": null
        }
      ]
    },
    "order": 19
  },
  {
    "id": "28aa501ef33780ab90f0f76715d948ff",
    "type": "heading_3",
    "parentId": "286a501ef33780798745d087320edfc0",
    "curriculumId": "286a501ef33780798745d087320edfc0",
    "pageId": "286a501ef33780798745d087320edfc0",
    "data": {
      "color": "default",
      "is_toggleable": false,
      "parent": [
        {
          "annotations": {
            "bold": false,
            "code": false,
            "color": "default",
            "italic": false,
            "strikethrough": false,
            "underline": false
          },
          "plain_text": "期待する出力結果",
          "href": null
        }
      ]
    },
    "order": 20
  },
  {
    "id": "28aa501ef3378033a637fba1ae9ff0ed",
    "type": "code",
    "parentId": "286a501ef33780798745d087320edfc0",
    "curriculumId": "286a501ef33780798745d087320edfc0",
    "pageId": "286a501ef33780798745d087320edfc0",
    "data": {
      "caption": [],
      "language": "plain text",
      "parent": [
        {
          "annotations": {
            "bold": false,
            "code": false,
            "color": "default",
            "italic": false,
            "strikethrough": false,
            "underline": false
          },
          "plain_text": "正答率を入力してください : 92.5\n秀",
          "href": null
        }
      ]
    },
    "order": 21
  },
  {
    "id": "28aa501ef337807ab5d0dd887c31e93c",
    "type": "code",
    "parentId": "286a501ef33780798745d087320edfc0",
    "curriculumId": "286a501ef33780798745d087320edfc0",
    "pageId": "286a501ef33780798745d087320edfc0",
    "data": {
      "caption": [],
      "language": "plain text",
      "parent": [
        {
          "annotations": {
            "bold": false,
            "code": false,
            "color": "default",
            "italic": false,
            "strikethrough": false,
            "underline": false
          },
          "plain_text": "正答率を入力してください : 77.2 \n良",
          "href": null
        }
      ]
    },
    "order": 22
  },
  {
    "id": "28aa501ef3378025a2add3b6293b7b0e",
    "type": "code",
    "parentId": "286a501ef33780798745d087320edfc0",
    "curriculumId": "286a501ef33780798745d087320edfc0",
    "pageId": "286a501ef33780798745d087320edfc0",
    "data": {
      "caption": [],
      "language": "plain text",
      "parent": [
        {
          "annotations": {
            "bold": false,
            "code": false,
            "color": "default",
            "italic": false,
            "strikethrough": false,
            "underline": false
          },
          "plain_text": "正答率を入力してください : 120\n不正な正答率です",
          "href": null
        }
      ]
    },
    "order": 23
  },
  {
    "id": "288a501ef33780439d5ae66a27053185",
    "type": "callout",
    "parentId": "286a501ef33780798745d087320edfc0",
    "curriculumId": "286a501ef33780798745d087320edfc0",
    "pageId": "286a501ef33780798745d087320edfc0",
    "data": {
      "color": "default_background",
      "icon": {
        "type": ""
      },
      "parent": [
        {
          "annotations": {
            "bold": false,
            "code": false,
            "color": "default",
            "italic": false,
            "strikethrough": false,
            "underline": false
          },
          "plain_text": "答え",
          "href": null
        }
      ]
    },
    "order": 24
  },
  {
    "id": "288a501ef337808a88dcf59a2c9f02e6",
    "type": "code",
    "parentId": "288a501ef33780439d5ae66a27053185",
    "curriculumId": "286a501ef33780798745d087320edfc0",
    "pageId": "286a501ef33780798745d087320edfc0",
    "data": {
      "caption": [],
      "language": "python",
      "parent": [
        {
          "annotations": {
            "bold": false,
            "code": false,
            "color": "default",
            "italic": false,
            "strikethrough": false,
            "underline": false
          },
          "plain_text": "# ユーザーから入力された正答率を、次の表に従って評価し、その評価を出力するプログラムを作成してください。\n# ただし、ユーザーからは実数（少数を含む数字）が入力されることも想定してください。\n# | 正答率    |評価|\n# | 90%～100% | 秀 |\n# | 80%～89%  | 優 |\n# | 70%～79%  | 良 |\n# | 60%～69%  | 可 |\n# | 0%～59%   | 不 |\n\nscore = float(input(\"正答率を入力してください : \"))\n\nif score \u003c= 100 and score \u003e= 90:\n    print(\"秀\")\nelif score \u003c 90 and score \u003e= 80:\n    print(\"優\")\nelif score \u003c 80 and score \u003e= 70:\n    print(\"良\")\nelif score \u003c 70 and score \u003e= 60:\n    print(\"可\")\nelif score \u003c 60 and score \u003e= 0:\n    print(\"不\")\nelse:\n    print(\"不正な正答率です\")",
          "href": null
        }
      ]
    },
    "order": 0
  },
  {
    "id": "288a501ef337808f841ae1c931b9cc6b",
    "type": "paragraph",
    "parentId": "286a501ef33780798745d087320edfc0",
    "curriculumId": "286a501ef33780798745d087320edfc0",
    "pageId": "286a501ef33780798745d087320edfc0",
    "data": {
      "color": "default",
      "parent": []
    },
    "order": 25
  }
]
